{
"type": "FeatureCollection",
"name": "10_Castildelgado",
"crs": { "type": "name", "properties": { "name": "urn:ogc:def:crs:OGC:1.3:CRS84" } },
"features": [
{ "type": "Feature", "properties": { "id": 10 }, "geometry": { "type": "Point", "coordinates": [ -3.085183241249257, 42.436672339425435 ] } }
]
}
