{
"type": "FeatureCollection",
"name": "45_Santiago_de_Compostela",
"crs": { "type": "name", "properties": { "name": "urn:ogc:def:crs:OGC:1.3:CRS84" } },
"features": [
{ "type": "Feature", "properties": { "id": 38 }, "geometry": { "type": "Point", "coordinates": [ -8.544297978326153, 42.880650878622099 ] } }
]
}
